[{"id":"b34359b8-3d44-4afc-b3b8-bad8a7d2be5a","created_at":"2026-03-04T22:34:00.50595+00:00","word":null,"source_file":"rare_words_12.txt","batch_index":3120,"words":[{"pos":"Verb","root":"መጠቀም","word":"አትጠቀሙባቸውም","synonyms":["to use","to utilize","to employ"],"importance":8},{"pos":"Noun","root":"ማራገፍ","word":"ማራገፊያ","synonyms":["unloading tool","duster","remover"],"importance":5},{"pos":"Noun","root":"ማመስገን","word":"ተመስጋኞች","synonyms":["the grateful","those who are thanked"],"importance":6},{"pos":"Verb","root":"መተካት","word":"የተተካውን","synonyms":["the replaced","the substituted"],"importance":7},{"pos":"Verb","root":"ማነሳሳት","word":"ካነሳሱት","synonyms":["if they motivated him","having inspired him"],"importance":6},{"pos":"Noun","root":"መድኀኒት","word":"መድኀኒቶች","synonyms":["medicines","drugs","remedies"],"importance":9},{"pos":"Verb","root":"መቀኘት","word":"ስለተቀኙበት","synonyms":["because they were composed for it","regarding the musical composition"],"importance":5},{"pos":"Verb","root":"መቀኘት","word":"ከመቀኘት","synonyms":["from composing","from singing"],"importance":5},{"pos":"Verb","root":"ማወቅ","word":"እንድናውቅላት","synonyms":["so that we may know for her"],"importance":6},{"pos":"Verb","root":"መውለድ","word":"ስለምትወልድለት","synonyms":["because she is giving birth for him"],"importance":6},{"pos":"Verb","root":"መክፈል","word":"እንድንከፍልላት","synonyms":["so that we may pay for her"],"importance":6}],"summary":"The input batch contained a mix of standard Amharic verbs/nouns and several proper nouns or OCR-corrupted strings (e.g., 'ዬሪ', 'ቲማንጌ', 'ኮካስ'). Proper nouns and non-lexical entities were discarded per the protocol to maintain dictionary integrity. Morphological analysis was applied to complex verbal forms to extract their infinitive citation roots. 'መድኀኒቶችንም' and 'ጉሌንና' were split to isolate the core nouns.","input_words":["አትጠቀሙባቸውም","ማራገፊያም","ተመስጋኞች","በመራሩ","የተተካውን","ካነሳሱትና","ዬሪ","ኮንችል","ቲማንጌ","ለካኒ","የጐደሬ","የገላሽ","አሽን","ኮካስ","ዩጋከን","ትንጐሽ","የመሀሽ","ጃርኩሜ","ኮሲያን","ጉሌንና","ኮቲል","መድኀኒቶችንም","የፍሎሬንቲን","ሚደቅሳም","ስለተቀኙበት","ከመቀኘት","ስላልተወላቸው","እንድናውቅላት","ስለምትወልድለት","እንድንከፍልላት"],"batch_number":105,"batch_label":"Words 3121-3150 (Batch 105/667)","model_version":null},{"id":"fd5f4cd5-718a-45a5-8834-ac86cbabec30","created_at":"2026-03-04T22:34:17.798456+00:00","word":null,"source_file":"rare_words_12.txt","batch_index":3600,"words":[{"pos":"Verb","root":"መጠራጠር","word":"ሊያስጠረጥረው","synonyms":["to cause suspicion","to make doubtful"],"importance":7},{"pos":"Verb","root":"መሳሳብ","word":"ይሳሳባሉ","synonyms":["they are attracted","they pull each other"],"importance":6},{"pos":"Verb","root":"መወሰን","word":"የወሰንኩ","synonyms":["that I decided","determined"],"importance":8},{"pos":"Adjective","root":"አጨቃጫቂ","word":"አጨቃጫቂዋ","synonyms":["controversial","argumentative"],"importance":7},{"pos":"Noun","root":"ሃላፊነት","word":"ከሃላፊነት","synonyms":["from responsibility","from duty"],"importance":9},{"pos":"Verb","root":"መታገድ","word":"ሲታገዱ","synonyms":["when suspended","when blocked"],"importance":8},{"pos":"Noun","root":"አይቲ","word":"የአይቲ","synonyms":["IT","Information Technology"],"importance":6},{"pos":"Noun","root":"ባለሙያ","word":"ባለሙያዋ","synonyms":["the professional","the expert"],"importance":7},{"pos":"Verb","root":"መተንተን","word":"እየተተነተኑ","synonyms":["being analyzed","being dissected"],"importance":7},{"pos":"Noun","root":"ንጉሥ","word":"ንጉሣቸው","synonyms":["their king","monarch"],"importance":8},{"pos":"Verb","root":"መልበስ","word":"እየተለበሱ","synonyms":["being worn","being dressed"],"importance":5},{"pos":"Verb","root":"ማቅረብ","word":"ያቀረበችባቸውን","synonyms":["that she presented against them"],"importance":7},{"pos":"Noun","root":"ክህደት","word":"ክህደቶች","synonyms":["betrayals","denials","treasons"],"importance":8},{"pos":"Verb","root":"መቅመስ","word":"ሊቀማመሱ","synonyms":["to taste","to sample"],"importance":6}],"summary":"The input batch contained significant OCR noise and non-lexical strings (e.g., 'ሜሌክሳዶ', 'ጋላህቲ', 'ሰጊ', 'ጋሀዲ', 'የሽታዚ'). These were discarded as they do not correspond to standard Amharic dictionary entries. Compound words like 'ከሃላፊነትሲታገዱ' and 'የአይቲባለሙያዋ' were split into meaningful morphological units. 'ያቅቧቸው' and 'ባሸትተው' were excluded due to high ambiguity and likely OCR corruption. The remaining words were lemmatized to their citation forms and categorized by POS.","input_words":["ሊያስጠረጥረው","ይሳሳባሉ","እፍስፍስ","የወሰንኩ","አጨቃጫቂዋ","የሀይላብ","ያቅቧቸው","ሜሌክሳዶ","ከሃላፊነትሲታገዱ","ቢያድግልኝና","የአይቲባለሙያዋ","እየተተነተኑና","ወብትና","ንጉሣቸውና","ጋላህቲ","ሰጊ","ጋሀዲ","የሽታዚ","እንድሆንላቸው","በዳስዋ","እየተለበሱ","ያቀረበችባቸውን","ከማስ","ገኘቱም","ከራማዳስ","ባሸትተው","የተቃጡት","ክህደቶች","የኦጎይ","ሊቀማመሱ"],"batch_number":121,"batch_label":"Words 3601-3630 (Batch 121/667)","model_version":null},{"id":"a94f3beb-3df0-4fb5-a184-6c3d0c948be2","created_at":"2026-03-04T22:33:54.393874+00:00","word":null,"source_file":"rare_words_12.txt","batch_index":2850,"words":[{"pos":"Verb","root":"ማውጣት","word":"በምናወጣው","synonyms":["extracting","issuing","producing"],"importance":7},{"pos":"Noun","root":"ፓርክ","word":"በየፓርኩ","synonyms":["in every park"],"importance":5},{"pos":"Verb","root":"መካተት","word":"ስለተካተተው","synonyms":["included","incorporated"],"importance":6},{"pos":"Noun","root":"ጎሳ","word":"በየጎሳው","synonyms":["every tribe","each clan"],"importance":5},{"pos":"Noun","root":"አልባሳት","word":"አልባሳቶቻቸውን","synonyms":["their clothes","their garments"],"importance":7},{"pos":"Noun","root":"ዕቃ","word":"ዕቃዎቼም","synonyms":["my items","my belongings"],"importance":6},{"pos":"Verb","root":"መጓዝ","word":"እጓዝበታለሁ","synonyms":["I will travel on it"],"importance":5},{"pos":"Noun","root":"ሠሌን","word":"ሠሌን","synonyms":["mat","woven reed"],"importance":4},{"pos":"Verb","root":"መናቅ","word":"አትናቁኝ","synonyms":["do not despise me","do not look down on me"],"importance":6},{"pos":"Noun","root":"ተዓማኒነት","word":"ተዓማኒነትህን","synonyms":["your credibility","your reliability"],"importance":8},{"pos":"Noun","root":"ረሃብተኛ","word":"የረሃብተኞቹና","synonyms":["the hungry ones","the starving"],"importance":7},{"pos":"Noun","root":"እጣፈንታ","word":"የእጣፈንታና","synonyms":["destiny","fate"],"importance":7}],"summary":"Processed 30 input tokens. Discarded 'ኢቮሎሃ', 'ከኢቲዮ', and 'እንድረሸን' as they appear to be OCR noise or non-standard proper nouns lacking dictionary roots. 'የምንተዳደደረው' was corrected to 'መተዳደር'. 'በየጉዱማሌው' was treated as a specific location/proper noun and excluded for lack of general lexical utility. Morphological analysis focused on extracting the infinitive citation form for all valid verbs and nouns.","input_words":["ስለዲቪ","በምናወጣው","ካለመገናኛ","በመንገታገት","በየፓርኩ","ስለተካተተው","የምንተዳደደረው","ኢቮሎሃ","በየጎሳውና","በየጉዱማሌው","ከማጣቸው","አልባሳቶቻቸውን","የሚደለደልለትና","ዕቃዎቼም","አለመፈተኔ","እጓዝበታለሁ","ሠሌን","እንደተሰነዘረባቸውና","አትናቁኝ","ተዓማኒነትህን","የረሃብተኞቹና","የእጣፈንታና","እንድረሸን","ተመቻችቶላቸውና","ከኢቲዮ","ስላችሁም","ምሥሪራችንን","ላይሞላው","የማዘወተር","ሲምታቱብንና"],"batch_number":96,"batch_label":"Words 2851-2880 (Batch 96/667)","model_version":null},{"id":"d3a9e70b-f35a-42f1-92ac-ef45f79c1639","created_at":"2026-03-04T22:34:00.470372+00:00","word":null,"source_file":"rare_words_12.txt","batch_index":3090,"words":[{"pos":"Verb","root":"ማስወሰን","word":"አስወስነናል","synonyms":["to cause to decide","to make someone determine"],"importance":7},{"pos":"Verb","root":"ማጽናናት","word":"ያጽናናውስ","synonyms":["to comfort","to console"],"importance":6},{"pos":"Verb","root":"መፍጠር","word":"የሚፈጥርና","synonyms":["creating","forming","generating"],"importance":8},{"pos":"Verb","root":"መንጸባረቅ","word":"የተንጸባረቀውም","synonyms":["reflected","shone","manifested"],"importance":7},{"pos":"Noun","root":"መቆረጫ","word":"መቆረጫህ","synonyms":["cutting tool","deadline","termination point"],"importance":5},{"pos":"Verb","root":"መድፈን","word":"መድፈናቸው","synonyms":["covering","plugging","filling"],"importance":6},{"pos":"Verb","root":"መዳረግ","word":"ተዳርገሻል","synonyms":["you have been driven to","you have been subjected to"],"importance":7},{"pos":"Verb","root":"መሆን","word":"የሚሆነውንም","synonyms":["that which happens","the becoming"],"importance":8},{"pos":"Verb","root":"መሆን","word":"የማይሆነውንም","synonyms":["that which does not happen","the impossible"],"importance":8},{"pos":"Verb","root":"መኮነን","word":"እየተኮነ","synonyms":["being condemned","being judged"],"importance":6},{"pos":"Verb","root":"ማውራት","word":"ያወራችኝን","synonyms":["what she told me","what she talked to me about"],"importance":7},{"pos":"Verb","root":"መጠቆም","word":"የሚጠቁምባቸው","synonyms":["that which indicates","used to point out"],"importance":7},{"pos":"Noun","root":"እጽ","word":"የእጸዋትና","synonyms":["plants","vegetation"],"importance":6},{"pos":"Noun","root":"በቅሎ","word":"በቅሎዎቹንና","synonyms":["mules"],"importance":5},{"pos":"Verb","root":"መጮህ","word":"የሚጮሁና","synonyms":["shouting","crying out","screaming"],"importance":6},{"pos":"Noun","root":"ቋሚነት","word":"ቋሚነቱን","synonyms":["permanence","stability","constancy"],"importance":7},{"pos":"Noun","root":"እሾህ","word":"በእሾኽ","synonyms":["thorn","prickle"],"importance":5},{"pos":"Verb","root":"ማስኬድ","word":"እናስኬዳቸዋለን","synonyms":["we will make them go","we will facilitate"],"importance":6},{"pos":"Verb","root":"መክፈል","word":"በተከፈለባቸው","synonyms":["paid for","divided into"],"importance":7}],"summary":"Processed 29 input tokens. Discarded 'በተቃረ', 'በበት', 'ባዝም', 'በጉሊና', 'ትምክህ' as they were either fragmented, OCR noise, or lacked clear semantic roots. Corrected 'የሚፍጠርና' to 'የሚፈጥርና' and 'የሚኮነውንም' to 'የሚሆነውንም' based on contextual probability. Split conjunctions (ና) from nouns/verbs where appropriate.","input_words":["እንዳታላሉ","አስወስነናል","ያጽናናውስ","የሚፍጠርና","የተንጸባረቀውም","በተቃረ","በበት","መቆረጫህ","እንዳልነሳ","መድፈናቸው","ተዳርገሻል","የፊንጫኣ","የሚኮነውንም","የማይኮነውንም","እየተኮነ","ያወራችኝን","ያልተላኩትና","የሚጠቁምባቸው","ባዝም","በጉሊና","የእጸዋትና","በቅሎዎቹንና","ከወሰደበት","የሚጮሁና","ትምክህ","ሲወጣጠርና","ቋሚነቱን","በእሾኽ","እናስኬዳቸዋለን","በተከፈለባቸው"],"batch_number":104,"batch_label":"Words 3091-3120 (Batch 104/667)","model_version":null},{"id":"6d576f3a-655c-4b9b-b5a6-e09a39c5099c","created_at":"2026-03-04T22:34:05.38699+00:00","word":null,"source_file":"rare_words_12.txt","batch_index":3360,"words":[{"pos":"Noun","root":"ገበያ","word":"የገቢያችሁ","synonyms":["market","bazaar","trade"],"importance":6},{"pos":"Verb","root":"መንገር","word":"እንዲነግርልኝ","synonyms":["to tell","to inform","to narrate"],"importance":7},{"pos":"Verb","root":"ማስገደድ","word":"የሚያስገድዷት","synonyms":["to force","to compel","to coerce"],"importance":8},{"pos":"Verb","root":"መቆፈር","word":"እንዳይቆፈር","synonyms":["to dig","to excavate"],"importance":5},{"pos":"Verb","root":"ማረፍ","word":"እንዳያርፉበት","synonyms":["to rest","to relax","to settle"],"importance":6},{"pos":"Verb","root":"ማሠልጠን","word":"ከማሠልጠንም","synonyms":["to train","to educate","to drill"],"importance":7},{"pos":"Verb","root":"ማሳከት","word":"ከማሳከት","synonyms":["to cause to fail","to frustrate"],"importance":4},{"pos":"Noun","root":"ባለዕዳ","word":"የባለዕዳነት","synonyms":["indebtedness","liability"],"importance":6},{"pos":"Verb","root":"ማሰብ","word":"ታስበን","synonyms":["to think","to consider","to plan"],"importance":7},{"pos":"Verb","root":"ማድረግ","word":"አታርጊኝ","synonyms":["to do","to make"],"importance":5},{"pos":"Verb","root":"ማምጣት","word":"ያመጣልሻል","synonyms":["to bring","to deliver"],"importance":7},{"pos":"Verb","root":"መኖር","word":"ምትኖር","synonyms":["to live","to exist","to reside"],"importance":8},{"pos":"Verb","root":"መተንበይ","word":"በመተንበዩም","synonyms":["to predict","to prophesy","to forecast"],"importance":6},{"pos":"Noun","root":"ውበት","word":"ውበቷንም","synonyms":["beauty","elegance","grace"],"importance":7},{"pos":"Verb","root":"መቀመር","word":"ከተቀመረ","synonyms":["to calculate","to compute","to formulate"],"importance":6},{"pos":"Verb","root":"መስጠት","word":"የሰጣቸውንም","synonyms":["to give","to provide","to grant"],"importance":8},{"pos":"Verb","root":"ማስቀመጥ","word":"እንደሚያስቀምጣት","synonyms":["to place","to set","to store"],"importance":7},{"pos":"Verb","root":"ማለፍ","word":"እንዳይታለፉና","synonyms":["to pass","to bypass","to skip"],"importance":6},{"pos":"Verb","root":"ማስጠንቀቅ","word":"እናስጠንቅቀው","synonyms":["to warn","to caution"],"importance":7},{"pos":"Verb","root":"መፋጀት","word":"በሚፋጁ","synonyms":["to burn","to scorch","to be intense"],"importance":5}],"summary":"Processed 25 input tokens. Discarded 'ሊቨንስ', 'በጎዴና', 'በሀርጌሌ', 'የገሊት', 'አምቻ', 'ኮሙኒኬ', 'ዲምሕት', 'ትሕዲን', 'እንዳልተቀረፁ', 'ቸንክሮ' due to being proper nouns, foreign loanwords, or OCR-corrupted nonsense that lacked clear dictionary roots. Standardized all verbs to their infinitive forms and categorized by POS.","input_words":["የገቢያችሁ","ሊቨንስ","እንዲነግርልኝ","የሚያስገድዷት","እንዳይቆፈር","እንዳያርፉበት","ከማሠልጠንም","ከማሳከት","የባለዕዳነት","ታስበን","አታርጊኝ","በጎዴና","በሀርጌሌ","ያመጣልሻል","ምትኖር","የገሊት","አምቻ","ኮሙኒኬ","ዲምሕት","ትሕዲን","እንዳልተቀረፁ","በመተንበዩም","ውበቷንም","ከተቀመረ","የሰጣቸውንም","እንደሚያስቀምጣት","ቸንክሮ","እንዳይታለፉና","እናስጠንቅቀው","በሚፋጁ"],"batch_number":113,"batch_label":"Words 3361-3390 (Batch 113/667)","model_version":null},{"id":"e1f43541-8fb8-429d-8519-4991349e8be4","created_at":"2026-03-04T22:34:09.747993+00:00","word":null,"source_file":"rare_words_12.txt","batch_index":3420,"words":[{"pos":"Verb","root":"መገለጥ","word":"ተገለጡላቸውና","synonyms":["to be revealed","to appear"],"importance":7},{"pos":"Verb","root":"መድፋት","word":"መድፋታችንን","synonyms":["to topple","to knock down","to defeat"],"importance":6},{"pos":"Noun","root":"መትረየስ","word":"ባለመትረየስ","synonyms":["machine gunner"],"importance":5},{"pos":"Verb","root":"መተኮስ","word":"ተኰሱበት","synonyms":["to shoot at"],"importance":8},{"pos":"Adjective","root":"ማደግ","word":"የበለደገ","synonyms":["grown","developed","prosperous"],"importance":6},{"pos":"Noun","root":"ገዳይ","word":"በገዳዮቹ","synonyms":["killers","murderers"],"importance":7},{"pos":"Verb","root":"መቀበል","word":"የምትቀበልው","synonyms":["receiving","accepting"],"importance":6},{"pos":"Noun","root":"ታዳሚ","word":"ታዳሚውስ","synonyms":["audience","attendee"],"importance":5},{"pos":"Verb","root":"መግፋት","word":"ቢገፋው","synonyms":["if he pushes","if he rejects"],"importance":5},{"pos":"Verb","root":"መፋታት","word":"የተፋታና","synonyms":["divorced","separated"],"importance":5},{"pos":"Verb","root":"መቆጣጠር","word":"መቆጣጠራቸውንና","synonyms":["controlling","supervising"],"importance":7},{"pos":"Verb","root":"መሰናዳት","word":"ተሰናድቶዋል","synonyms":["prepared","arranged"],"importance":6},{"pos":"Verb","root":"መጥረግ","word":"ተጠርጎዋል","synonyms":["swept","cleared"],"importance":6},{"pos":"Verb","root":"ማቅረብ","word":"እንዳቀረበም","synonyms":["as he presented","as he submitted"],"importance":6},{"pos":"Verb","root":"መነገር","word":"ሲነገርስ","synonyms":["when it is said","while being told"],"importance":5},{"pos":"Verb","root":"መከናነብ","word":"ሲከናነቡት","synonyms":["wrapping oneself","covering"],"importance":4},{"pos":"Verb","root":"ማውራት","word":"በማውራቱ","synonyms":["by talking","by speaking"],"importance":5},{"pos":"Verb","root":"መደማት","word":"የደማሁበትና","synonyms":["where I bled"],"importance":6},{"pos":"Verb","root":"መቁሰል","word":"የቆሰልኩለበት","synonyms":["for which I was wounded"],"importance":6},{"pos":"Verb","root":"መሰደብ","word":"የተሰደብኩበት","synonyms":["for which I was insulted"],"importance":6},{"pos":"Noun","root":"ሞዛምቢካዊ","word":"ሞዛምቢካዊው","synonyms":["Mozambican"],"importance":5},{"pos":"Noun","root":"ትዳር","word":"እስከትዳር","synonyms":["until marriage"],"importance":5},{"pos":"Verb","root":"መስተካከል","word":"ተስተካከለና","synonyms":["it was fixed","it was adjusted"],"importance":6},{"pos":"Verb","root":"ማሸነፍ","word":"አሸነፉም","synonyms":["they won","they defeated"],"importance":7},{"pos":"Verb","root":"መሰረዝ","word":"መሰረዝንና","synonyms":["cancellation","deleting"],"importance":5}],"summary":"Processed 30 input tokens. Discarded 'ጀኪፕቾግ' (proper noun/foreign name), 'ጣዮችና' (likely OCR error for 'ጣዮች'), 'የኔቢጢዋም' (colloquial/slang), and 'በአብዱርከሪም' (proper noun). Applied morphological lemmatization to verbs and nouns. Corrected minor OCR visual artifacts in 'ተሰናድቶዋል' and 'ተጠርጎዋል'.","input_words":["ጀኪፕቾግ","ተገለጡላቸውና","መድፋታችንን","ጣዮችና","ባለመትረየስ","ተኰሱበት","የበለደገ","በገዳዮቹ","የምትቀበልው","የኔቢጢዋም","ታዳሚውስ","ቢገፋው","የተፋታና","መቆጣጠራቸውንና","ተሰናድቶዋል","ተጠርጎዋል","በሚበዛበትና","እንዳቀረበም","ሲነገርስ","በአብዱርከሪም","ሲከናነቡት","በማውራቱ","የደማሁበትና","የቆሰልኩለበት","የተሰደብኩበት","ሞዛምቢካዊው","እስከትዳር","ተስተካከለና","አሸነፉም","መሰረዝንና"],"batch_number":115,"batch_label":"Words 3421-3450 (Batch 115/667)","model_version":null},{"id":"c59cbffc-afe2-4ac2-a32a-cb1ec174540a","created_at":"2026-03-04T22:34:14.35914+00:00","word":null,"source_file":"rare_words_12.txt","batch_index":3570,"words":[{"pos":"Verb","root":"ማጠነጠን","word":"እያጠነጠኑ","synonyms":["focusing","centering","revolving around"],"importance":7},{"pos":"Verb","root":"መክበስ","word":"ከብሰው","synonyms":["surrounding","encircling","enveloping"],"importance":6},{"pos":"Verb","root":"መጎረስ","word":"ሲጎርሱ","synonyms":["feeding","morseling","eating"],"importance":5},{"pos":"Noun","root":"ችሎት","word":"ስለችሎት","synonyms":["court","tribunal","hearing"],"importance":8},{"pos":"Verb","root":"ማንፀባረቅ","word":"በማንፀባረቃቸው","synonyms":["reflecting","radiating","demonstrating"],"importance":7},{"pos":"Verb","root":"ማምጣት","word":"ቢያመጣቸውም","synonyms":["bringing","delivering","causing"],"importance":6},{"pos":"Verb","root":"መተውለበለብ","word":"የተውለበለበውና","synonyms":["fluttering","waving","dangling"],"importance":5},{"pos":"Verb","root":"መንገብገብ","word":"የሚንገበገብ","synonyms":["burning","yearning","suffering"],"importance":7},{"pos":"Noun","root":"ማርክሳዊ","word":"ማርክሳውያን","synonyms":["Marxists"],"importance":8},{"pos":"Verb","root":"መፈረም","word":"አልፈረሙ","synonyms":["did not sign","did not endorse"],"importance":7},{"pos":"Verb","root":"መበጀት","word":"አይበጅላቸውም","synonyms":["does not benefit them","does not suit them"],"importance":6},{"pos":"Verb","root":"መታሸግ","word":"ለሚታሸጉ","synonyms":["to be sealed","to be packed"],"importance":5},{"pos":"Noun","root":"ጣሪያ","word":"ጣሪያዎቹ","synonyms":["roofs","ceilings"],"importance":6},{"pos":"Verb","root":"መሰባበር","word":"እንደተሰባበሩ","synonyms":["as they were broken","shattered"],"importance":6},{"pos":"Noun","root":"አስተጣጠፍ","word":"አስተጣጠፍ","synonyms":["folding style","arrangement","construction"],"importance":5},{"pos":"Verb","root":"መደማመር","word":"ተደማምረውም","synonyms":["added together","combined","aggregated"],"importance":6},{"pos":"Noun","root":"ዕውነት","word":"ከዕውነቱ","synonyms":["from the truth","from reality"],"importance":8}],"summary":"Processed 25 input tokens. Discarded 'እስኪፈጥ', 'መሳድ', 'ባብዛኝኖቹ', 'ያለመገጠ', 'ማቸውንና', 'ኣየን', 'መቺዉን', 'ኣበሳ', 'ሊጋጥም', 'ከተማኙ', 'ተከዝኩ' due to OCR corruption, non-standard morphology, or lack of clear semantic root. Split 'የተውለበለበውና' and 'ተደማምረውም' to isolate core roots. Corrected orthographic inconsistencies in 'ዕውነቱ' and 'ማርክሳውያን'.","input_words":["እያጠነጠኑ","ከብሰው","እስኪፈጥ","ሲጎርሱ","ሊያጎርሱሽ","ስለችሎት","በማንፀባረቃቸው","ቢያመጣቸውም","የተውለበለበውና","መሳድ","የሚንገበገብ","ማርክሳውያን","ባብዛኝኖቹ","አልፈረሙ","አይበጅላቸውም","ለሚታሸጉ","ጣጠለ","ጣሪያዎቹ","ያለመገጠ","ማቸውንና","እንደተሰባበሩ","ኣየን","መቺዉን","ኣበሳ","ሊጋጥም","ከተማኙ","ተከዝኩ","አስተጣጠፍ","ተደማምረውም","ከዕውነቱ"],"batch_number":120,"batch_label":"Words 3571-3600 (Batch 120/667)","model_version":null},{"id":"2f147f4a-73af-4d96-a47a-162da8667719","created_at":"2026-03-04T22:34:37.369055+00:00","word":null,"source_file":"rare_words_12.txt","batch_index":3660,"words":[{"pos":"Verb","root":"መምረጥ","word":"እንደመረጥሁና","synonyms":["to choose","to select","to elect"],"importance":7},{"pos":"Verb","root":"መስልጠን","word":"ባልሠለጠንሁበት","synonyms":["to be trained","to be civilized","to be skilled"],"importance":6},{"pos":"Verb","root":"መንካት","word":"ነክቷችኋል","synonyms":["to touch","to affect","to concern"],"importance":8},{"pos":"Verb","root":"መወትወት","word":"ከመወትወቱ","synonyms":["to insist","to pester","to urge"],"importance":5},{"pos":"Noun","root":"ይቅርታ","word":"ይቅርታችሁ","synonyms":["forgiveness","apology","pardon"],"importance":9},{"pos":"Verb","root":"ማስገኘት","word":"ስላስገኘላት","synonyms":["to cause to obtain","to provide","to yield"],"importance":7},{"pos":"Adjective","root":"ልማደኛ","word":"በልማደኛው","synonyms":["habitual","customary","traditional"],"importance":6},{"pos":"Verb","root":"ማካሄድ","word":"የማካሄድን","synonyms":["to conduct","to carry out","to manage"],"importance":8},{"pos":"Verb","root":"መኖር","word":"ሳይኖርበትም","synonyms":["to exist","to reside","to be present"],"importance":7},{"pos":"Verb","root":"መብለጥ","word":"ይበልጡብኛል","synonyms":["to exceed","to surpass","to be better than"],"importance":6},{"pos":"Verb","root":"መገላማጥ","word":"መገላማጥ","synonyms":["to glare at","to stare aggressively"],"importance":4},{"pos":"Verb","root":"ማሸነፍ","word":"ስለማሸነፋቸው","synonyms":["to win","to defeat","to overcome"],"importance":8},{"pos":"Noun","root":"መውጫ","word":"በመውጪያ","synonyms":["exit","outlet","way out"],"importance":7},{"pos":"Verb","root":"መቻኮል","word":"ከተቻኮለ","synonyms":["to rush","to hurry"],"importance":5},{"pos":"Verb","root":"ማውጣት","word":"እንዳወጣጡ","synonyms":["to take out","to extract","to produce"],"importance":6},{"pos":"Noun","root":"አገባብ","word":"ለአገባቡም","synonyms":["usage","context","manner of entry"],"importance":7},{"pos":"Verb","root":"መጣደፍ","word":"ብንጣደፍ","synonyms":["to rush","to be in a hurry"],"importance":5},{"pos":"Verb","root":"መኮትኮት","word":"እየኮተኮትን","synonyms":["to hoe","to cultivate","to nurture"],"importance":5},{"pos":"Verb","root":"መስቀል","word":"ወደሰቀለው","synonyms":["to hang","to crucify","to suspend"],"importance":6}],"summary":"Processed 20 input tokens. Discarded 'የተቀበተተ' (OCR error), 'ኪሶዚ' (nonsense), 'ሎቬል' (proper noun/foreign), 'መታጥ' (incomplete), 'ቱኒዘያን' (proper noun), 'አሊመሐመድ' (proper noun), 'ከብሩም' (ambiguous/fragment), 'ቴካቴቭ' (nonsense), and 'ቭትሀቲሙ' (nonsense). Successfully lemmatized verbs and nouns, ensuring all entries meet the 2-character minimum length requirement.","input_words":["የተቀበተተ","እንደመረጥሁና","ባልሠለጠንሁበት","ስፈተፍት","ኪሶዚ","ነክቷችኋል","ከመወትወቱ","ይቅርታችሁ","ስላስገኘላት","በልማደኛው","ሎቬል","መታጥ","ቱኒዘያን","የማካሄድን","አሊመሐመድ","ሳይኖርበትም","ይበልጡብኛል","መገላማጥ","ስለማሸነፋቸው","በመውጪያ","ከተቻኮለ","እንዳወጣጡ","ለአገባቡም","ብንጣደፍ","ከብሩም","የኑሐሚን","እየኮተኮትን","ቴካቴቭ","ቭትሀቲሙ","ወደሰቀለው"],"batch_number":123,"batch_label":"Words 3661-3690 (Batch 123/667)","model_version":null},{"id":"f65bf5ca-c948-4d4d-ae11-6b4e2ca53f42","created_at":"2026-03-04T22:34:41.429665+00:00","word":null,"source_file":"rare_words_12.txt","batch_index":3750,"words":[{"pos":"Noun","root":"ማጨስ","word":"አጫሾች","synonyms":["smokers"],"importance":6},{"pos":"Noun","root":"መሾም","word":"ተሾሚ","synonyms":["appointee","nominee"],"importance":5},{"pos":"Noun","root":"ወንድም","word":"ወንድሙ","synonyms":["brother"],"importance":7},{"pos":"Noun","root":"መቐሌ","word":"መቐሌ","synonyms":["Mekelle"],"importance":8},{"pos":"Verb","root":"መክፈት","word":"እከፍተዋለሁ","synonyms":["I will open it"],"importance":6},{"pos":"Noun","root":"መልከጻዲቅ","word":"መልከጻዲቅ","synonyms":["Melchizedek"],"importance":4},{"pos":"Verb","root":"መከተት","word":"ይከትትበታል","synonyms":["he inserts into it","he stuffs into it"],"importance":5},{"pos":"Verb","root":"መበቀል","word":"ተበቀልካቸው","synonyms":["you avenged them"],"importance":6},{"pos":"Noun","root":"መዋጥ","word":"አለመዋጥ","synonyms":["not swallowing","indigestion"],"importance":5},{"pos":"Noun","root":"ዘግናኝ","word":"ዘግናኝነት","synonyms":["horror","atrocity","gruesomeness"],"importance":7},{"pos":"Verb","root":"ማጋባት","word":"የምናጋባው","synonyms":["that we are marrying off","that we are joining"],"importance":5},{"pos":"Noun","root":"መስፈርት","word":"መስፈርቶቹ","synonyms":["criteria","requirements"],"importance":8},{"pos":"Noun","root":"መጻፍ","word":"ጽሕፈት","synonyms":["writing","script","manuscript"],"importance":7},{"pos":"Verb","root":"ማነስ","word":"አንሰውም","synonyms":["they are not less","they are not small"],"importance":5},{"pos":"Verb","root":"መብዛት","word":"በዝተውም","synonyms":["and they increased","and they are many"],"importance":6},{"pos":"Noun","root":"መስዋዕት","word":"መስዋዕት","synonyms":["sacrifice","offering"],"importance":8},{"pos":"Noun","root":"መደበላለቅ","word":"ከመደበላለቁ","synonyms":["from the mixing","from the confusion"],"importance":6},{"pos":"Verb","root":"ማመናመን","word":"ሊያመናምነው","synonyms":["to make it thin","to diminish it"],"importance":5},{"pos":"Verb","root":"መከራየት","word":"መከራየት","synonyms":["to rent","to hire"],"importance":7}],"summary":"Processed 30 input tokens. Discarded 'በትኘ', 'ሱዓወ', 'ኧርነርስት', 'ተናት', 'የጽፁፍ', 'አይጭንበትም', 'የግርማይ' due to OCR noise, non-standard orthography, or lack of clear semantic root. Split 'ወንድሙንና' into 'ወንድሙ' and 'ና' (discarded conjunction), 'መስዋዕትና' into 'መስዋዕት' and 'ና'. Corrected 'ጽሕፈትየ' to 'ጽሕፈት'. Lemmatized all verbs to their infinitive forms.","input_words":["አጫሾችም","ከሚንጎማለሉት","ተሾሚ","ለአደረገው","ኹዛዒን","ወንድሙንና","የመቐሌን","እከፍተዋለሁ","በትኘ","ሱዓወ","መልከጻዲቅ","ይከትትበታል","ኧርነርስት","ተናት","ተበቀልካቸው","አለመዋጥ","የመሰቀሉም","ዘግናኝነት","የምናጋባው","ከመስፈርቶቹም","ጽሕፈትየ","አንሰውም","በዝተውም","መስዋዕትና","የጽፁፍ","አይጭንበትም","ከመደበላለቁ","ሊያመናምነው","የግርማይ","መከራየትም"],"batch_number":126,"batch_label":"Words 3751-3780 (Batch 126/667)","model_version":null},{"id":"849c3fcc-dde8-4b67-8347-4ed2e954eae2","created_at":"2026-03-04T22:34:09.733928+00:00","word":null,"source_file":"rare_words_12.txt","batch_index":3480,"words":[{"pos":"Noun","root":"ሎኮሞቲቭ","word":"ሎኮምቲቭ","synonyms":["Locomotive","Train engine"],"importance":6},{"pos":"Noun","root":"ሥልጣኔ","word":"ሥልጣኔውም","synonyms":["Civilization","Culture"],"importance":8},{"pos":"Verb","root":"መጠየቅ","word":"ያልጠየኳቸው","synonyms":["Unasked","Not questioned"],"importance":7},{"pos":"Verb","root":"ማቄም","word":"ያቄሙብኛል","synonyms":["Resent","Hold a grudge"],"importance":6},{"pos":"Verb","root":"መደበር","word":"እየደበረኝም","synonyms":["Bored","Feeling dull"],"importance":5},{"pos":"Verb","root":"ማንኳኳት","word":"አላንኳኳም","synonyms":["Did not knock"],"importance":4},{"pos":"Verb","root":"ማሳመን","word":"ያላሳመነው","synonyms":["Unconvinced","Not persuaded"],"importance":7},{"pos":"Verb","root":"መስጠት","word":"አይሰጥኽም","synonyms":["Will not give"],"importance":5},{"pos":"Adverb","root":"እንግዲህ","word":"ከእንግዲኽ","synonyms":["Henceforth","From now on"],"importance":8},{"pos":"Verb","root":"መርገጥ","word":"የሚረገጥ","synonyms":["Trampled","Stepped on"],"importance":5},{"pos":"Verb","root":"መታደል","word":"የታደላትን","synonyms":["Blessed","Fortunate"],"importance":6},{"pos":"Noun","root":"ህብረተሰብ","word":"ህብረተሠባዊው","synonyms":["Societal","Social"],"importance":9},{"pos":"Noun","root":"ተፈጥሮ","word":"ተፍጥሮን","synonyms":["Nature","Creation"],"importance":8},{"pos":"Noun","root":"ትምህርት","word":"ከትምሕርቱ","synonyms":["Education","Lesson"],"importance":9}],"summary":"Processed 25 input tokens. Discarded non-standard or unrecoverable OCR noise such as 'በዑጽ', 'ይተገትገው', 'ተፍነክንኬ', and 'እንዳደገደግሁ' due to lack of clear lexicographical root or semantic ambiguity. Standardized orthography (e.g., 'ተፍጥሮን' to 'ተፈጥሮ') and lemmatized verbs to their infinitive forms. 'ሎኮምቲቭ' was corrected to 'ሎኮሞቲቭ' for dictionary accuracy.","input_words":["የሎኮምቲቭ","በዑጽ","የተከላካላይ","ሥልጣኔውም","ይተገትገው","ያልጠየኳቸው","ያቄሙብኛል","እየደበረኝም","አላንኳኳም","ያላሳመነው","አይሰጥኽም","ከእንግዲኽ","ያልኹት","ኾንኩ","የሚረገጥ","የታሠርከው","ተፍነክንኬ","የታደላትን","እንዳደገደግሁ","ካላልሁማ","ባይልኳቸው","ታልቅሥ","ህብረተሠባዊው","ከተዥጐረጐረ","ተፍጥሮን","እንዳላመጠች","ትሁንባችሁ","ካላበጀን","የነብሩት","ከትምሕርቱ"],"batch_number":117,"batch_label":"Words 3481-3510 (Batch 117/667)","model_version":null}]