[{"id":"a867e07b-50c0-44c2-ac95-1cd830baea8e","created_at":"2026-02-25T20:17:35.959542+00:00","word":null,"source_file":"rare_words_18/chunk_0446.txt","batch_index":0,"words":[{"pos":"Noun","root":"ሚሌት","word":"ሚሌትን","synonyms":["Miletus","Milet"],"importance":5},{"pos":"Adjective","root":"ባለስሜት","word":"ባለስሜቱ","synonyms":["passionate","emotional","sensitive","feeling"],"importance":7},{"pos":"Verb","root":"መጠበቅ","word":"ይጠበቅዋል","synonyms":["to be expected","to wait","to anticipate","to guard"],"importance":8},{"pos":"Noun","root":"ጌድሶን","word":"በጌድሶን","synonyms":["Gershon","Gedson"],"importance":5},{"pos":"Noun","root":"ሜራሪ","word":"በሜራሪ","synonyms":["Merari"],"importance":5},{"pos":"Adjective","root":"አረማዊ","word":"አረማዊውን","synonyms":["pagan","heathen","gentile","infidel"],"importance":7},{"pos":"Verb","root":"መቀባት","word":"ላልተቀቡ","synonyms":["to be anointed","to paint","to smear","to coat"],"importance":8},{"pos":"Verb","root":"ማንጋጋት","word":"አንጋግተው","synonyms":["to swarm","to crowd","to flock","to gather in mass"],"importance":6},{"pos":"Noun","root":"ዘበኛ","word":"ዘበኞቼን","synonyms":["guard","sentinel","watchman","security"],"importance":8},{"pos":"Verb","root":"መሰቃየት","word":"አትሰቃዩም","synonyms":["to suffer","to be tormented","to be tortured","to agonize"],"importance":9},{"pos":"Verb","root":"ማሰማት","word":"ላሰሙን","synonyms":["to inform","to announce","to sound","to make heard"],"importance":7},{"pos":"Verb","root":"ማጠንከር","word":"አጠነከራት","synonyms":["to strengthen","to fortify","to reinforce","to toughen"],"importance":8},{"pos":"Verb","root":"መኳተን","word":"እንደኳተኑ","synonyms":["to wander","to toil","to struggle","to roam"],"importance":6},{"pos":"Verb","root":"መክሰም","word":"እየከሠመ","synonyms":["to fade","to vanish","to diminish","to subside"],"importance":7},{"pos":"Verb","root":"መነጋገር","word":"ተነጋገረን","synonyms":["to converse","to discuss","to speak with","to negotiate"],"importance":8},{"pos":"Verb","root":"ማነስ","word":"አነሠው","synonyms":["to be insufficient","to be small","to decrease","to be less"],"importance":7},{"pos":"Verb","root":"መማረክ","word":"የማረኩትንና","synonyms":["to capture","to take prisoner","to captivate","to charm"],"importance":8},{"pos":"Verb","root":"መፈጸም","word":"እንደተፈጸሙበት","synonyms":["to fulfill","to execute","to complete","to perform"],"importance":9},{"pos":"Verb","root":"መዝለቅ","word":"አይዘልቅምም","synonyms":["to last","to endure","to penetrate","to go through"],"importance":7},{"pos":"Verb","root":"ማንበብ","word":"አነብለት","synonyms":["to read"],"importance":8},{"pos":"Noun","root":"ገሹራውያን","word":"የገሹራውያን","synonyms":["Geshurites"],"importance":5},{"pos":"Noun","root":"አዊም","word":"የአዊም","synonyms":["Avvites"],"importance":5},{"pos":"Noun","root":"መአራ","word":"መአራ","synonyms":["Mearah"],"importance":5},{"pos":"Noun","root":"ጌባላውያን","word":"የጌባላውያን","synonyms":["Gebalites"],"importance":5},{"pos":"Noun","root":"ሚስረፎትማይም","word":"ሚስረፎትማይም","synonyms":["Misrephoth-maim"],"importance":5},{"pos":"Noun","root":"ሌቲባም","word":"ሌቲባም","synonyms":["Lethibam"],"importance":4},{"pos":"Verb","root":"ማስቀመጥ","word":"አያስቀምጡንም","synonyms":["to place","to set","to seat","to keep","to let stay"],"importance":8},{"pos":"Noun","root":"ማጥቆር","word":"የማጥቆሪያ","synonyms":["blackening tool","darkening instrument"],"importance":6},{"pos":"Verb","root":"ማጥቆር","word":"ማጥቆርና","synonyms":["to blacken","to darken","to char"],"importance":6},{"pos":"Verb","root":"መሮጥ","word":"የሮጠችበት","synonyms":["to run","to race","to dash"],"importance":8}],"summary":"The input batch primarily contains biblical terminology and complex Amharic verbs. I identified and corrected archaic character usage (e.g., ሠ to ሰ in 'አነሠው' and 'እየከሠመ') for lemmatization. Merged conjunctions (e.g., -እና, -ም) were analyzed to isolate the core semantic units. Proper nouns related to biblical geography and genealogy (Gershon, Merari, Geshurites, etc.) were preserved and mapped to their English equivalents. All verbs were reduced to their infinitive (መነሻ ቃል) forms for dictionary-grade accuracy.","input_words":["ሚሌትን","ባለስሜቱ","ይጠበቅዋል","በጌድሶን","በሜራሪ","አረማዊውን","ላልተቀቡ","አንጋግተው","ዘበኞቼን","አትሰቃዩም","ላሰሙን","አጠነከራት","እንደኳተኑ","እየከሠመ","ተነጋገረን","አነሠው","የማረኩትንና","እንደተፈጸሙበት","አይዘልቅምም","አነብለት","የገሹራውያን","የአዊም","መአራ","የጌባላውያን","ሚስረፎትማይም","ሌቲባም","አያስቀምጡንም","የማጥቆሪያ","ማጥቆርና","የሮጠችበት"],"batch_number":null,"batch_label":null,"model_version":null},{"id":"dfeda79b-c2bb-4d90-86fb-2c87187f0d85","created_at":"2026-02-25T20:18:34.099422+00:00","word":null,"source_file":"rare_words_18/chunk_0452.txt","batch_index":0,"words":[{"pos":"Verb","root":"መመዘን","word":"ትመዝኑ","synonyms":["weigh","evaluate","assess","measure"],"importance":8},{"pos":"Noun","root":"እድገት","word":"ዕድገቶቹ","synonyms":["growth","progress","development","advancement"],"importance":9},{"pos":"Verb","root":"መወልተት","word":"ወስልተኻል","synonyms":["shirk","idle","be lazy","procrastinate"],"importance":7},{"pos":"Noun","root":"መግለጫ","word":"የገለፃው","synonyms":["statement","explanation","description","briefing"],"importance":8},{"pos":"Noun","root":"ናይጀሪያ","word":"የናይጀሪያንና","synonyms":["Nigeria"],"importance":6},{"pos":"Verb","root":"መሸፋፈን","word":"የተሸፋፈኑበትን","synonyms":["cover up","conceal","hide","camouflage"],"importance":8},{"pos":"Verb","root":"መመሰል","word":"ስለተመሳሰለብኝ","synonyms":["resemble","look like","simulate","appear"],"importance":8},{"pos":"Verb","root":"ማየት","word":"እንዲያዩትም","synonyms":["see","look","watch","observe"],"importance":9},{"pos":"Noun","root":"ጌድዮን","word":"ለጌድዮንና","synonyms":["Gideon"],"importance":5},{"pos":"Verb","root":"መጥረግ","word":"ሰጣርገው","synonyms":["sweep","wipe","clean","clear"],"importance":7},{"pos":"Verb","root":"መታዘዝ","word":"ያልታዘዘልን","synonyms":["obey","be ordered","be commanded","submit"],"importance":8},{"pos":"Verb","root":"መባስ","word":"ይብስብን","synonyms":["worsen","deteriorate","aggravate","get worse"],"importance":8},{"pos":"Noun","root":"ገንፎ","word":"ከገንፎው","synonyms":["porridge","mush","pudding"],"importance":7},{"pos":"Verb","root":"መጭለፍ","word":"እየጨለፈችልኝ","synonyms":["scoop","ladle","dip","draw out"],"importance":7},{"pos":"Verb","root":"መሞከር","word":"ሲሞክርና","synonyms":["try","attempt","test","experiment"],"importance":9},{"pos":"Verb","root":"መቻል","word":"እንደማይችልበት","synonyms":["can","be able","manage","afford"],"importance":9},{"pos":"Noun","root":"አጥፊነት","word":"አጥፊነትንና","synonyms":["destructiveness","harmfulness","delinquency","malice"],"importance":7},{"pos":"Noun","root":"ክፍትነት","word":"ክፍታፍነት","synonyms":["openness","transparency","candor"],"importance":7},{"pos":"Noun","root":"ጮካ","word":"በጮካ","synonyms":["Choke Mountain","highland"],"importance":6},{"pos":"Noun","root":"ጌታ","word":"ጌቶቹንም","synonyms":["lord","master","owner","sir"],"importance":8},{"pos":"Noun","root":"እመቤት","word":"እመቤቶቹንም","synonyms":["lady","mistress","hostess","madam"],"importance":8},{"pos":"Verb","root":"መርዳት","word":"ትረጅናለሽ","synonyms":["help","assist","aid","support"],"importance":9},{"pos":"Noun","root":"አርዱፍ","word":"በአርዱፍና","synonyms":["Arduf"],"importance":4},{"pos":"Noun","root":"ፍሩድ","word":"በፍሩድ","synonyms":["Frud"],"importance":4},{"pos":"Verb","root":"ማቃጠል","word":"እያቃጠለውም","synonyms":["burn","ignite","set on fire","scorch"],"importance":8},{"pos":"Noun","root":"አከርካሪ","word":"የአከርካሪዬ","synonyms":["spine","backbone","spinal column"],"importance":7},{"pos":"Noun","root":"አዲሎ","word":"አዲሎም","synonyms":["Adilo"],"importance":5},{"pos":"Verb","root":"ማብራራት","word":"እንዳብራራችልን","synonyms":["explain","clarify","elucidate","illustrate"],"importance":8},{"pos":"Noun","root":"ዳይሬክቶሬት","word":"የዳይሬክቶሪቱ","synonyms":["directorate","department","office"],"importance":8}],"summary":"The batch was processed with a focus on morphological restoration and OCR error correction. A significant split was performed on 'የዳይሬክ' and 'ቶሪቱ', merging them into the single valid term 'የዳይሬክቶሪቱ' (of the directorate). Visual OCR noise in 'ክፍታፍነት' was interpreted as 'ክፍትነት' (openness) based on common administrative context. Proper nouns like 'አርዱፍ', 'ፍሩድ', and 'ጮካ' were preserved as citation forms. Lemmatization was applied to complex verb forms (e.g., 'እየጨለፈችልኝ' to 'መጭለፍ') to provide accurate dictionary roots.","input_words":["ትመዝኑ","ዕድገቶቹ","ወስልተኻል","የገለፃው","የናይጀሪያንና","የተሸፋፈኑበትን","ስለተመሳሰለብኝ","እንዲያዩትም","ለጌድዮንና","ሰጣርገው","ያልታዘዘልን","ይብስብን","ከገንፎው","እየጨለፈችልኝ","ሲሞክርና","እንደማይችልበት","አጥፊነትንና","ክፍታፍነት","በጮካ","ጌቶቹንም","እመቤቶቹንም","ትረጅናለሽ","በአርዱፍና","በፍሩድ","እያቃጠለውም","የአከርካሪዬ","አዲሎም","እንዳብራራችልን","የዳይሬክ","ቶሪቱ"],"batch_number":null,"batch_label":null,"model_version":null},{"id":"f75beb2e-9925-4891-8136-ba9420b2a016","created_at":"2026-02-25T20:18:34.279723+00:00","word":null,"source_file":"rare_words_18/chunk_0444.txt","batch_index":0,"words":[{"pos":"Verb","root":"ማጥበቅ","word":"ያጠበቀውም","synonyms":["tighten","strengthen","reinforce","fasten"],"importance":7},{"pos":"Verb","root":"መጸየፍ","word":"እንጠየፈው","synonyms":["abhor","loathe","detest","recoil"],"importance":6},{"pos":"Verb","root":"መሰንጠቅ","word":"ተሰነጠቀና","synonyms":["split","crack","fracture","cleave"],"importance":7},{"pos":"Verb","root":"መሰልጠን","word":"እንደሚሠለጥኑበት","synonyms":["train","master","practice","become civilized"],"importance":8},{"pos":"Verb","root":"ማስፈር","word":"ያሰፈርኳት","synonyms":["record","write down","settle","inscribe"],"importance":7},{"pos":"Verb","root":"ማጽናት","word":"ያፅናህ","synonyms":["comfort","console","strengthen","solidify"],"importance":8},{"pos":"Noun","root":"መግለጫ","word":"መግለጫዬን","synonyms":["statement","press release","explanation","briefing"],"importance":9},{"pos":"Verb","root":"መንፈግ","word":"አልነፈኩትም","synonyms":["deny","withhold","refuse","deprive"],"importance":7},{"pos":"Verb","root":"ማሰኘት","word":"የሚያሰኛቸውንና","synonyms":["cause to desire","make one feel","induce"],"importance":6},{"pos":"Verb","root":"መገፋፋት","word":"የሚገፋፋቸውንም","synonyms":["encourage","incite","push","motivate"],"importance":7},{"pos":"Noun","root":"መውደቂያ","word":"መውደቂያችን","synonyms":["downfall","resting place","end","destination"],"importance":7},{"pos":"Noun","root":"ኮርፖሬሽን","word":"በኮርፖሬሽኑና","synonyms":["corporation","company","enterprise","firm"],"importance":8},{"pos":"Verb","root":"ማድረግ","word":"ያደረገዋልም","synonyms":["do","make","perform","act"],"importance":9},{"pos":"Verb","root":"መፈለግ","word":"ትፈልጋችኋለች","synonyms":["want","seek","desire","search"],"importance":9},{"pos":"Noun","root":"ማመልከቻ","word":"ማመልከቻዎችና","synonyms":["application","petition","request","form"],"importance":8},{"pos":"Verb","root":"ማሰናበት","word":"ለማያሰናብት","synonyms":["dismiss","fire","release","discharge"],"importance":7},{"pos":"Verb","root":"መደገፍ","word":"ይደግፉዋቸው","synonyms":["support","uphold","back","prop"],"importance":8},{"pos":"Verb","root":"መንጠቅ","word":"የነጠቀቻት","synonyms":["snatch","seize","grab","rob"],"importance":7},{"pos":"Noun","root":"ዓይነት","word":"ዓይነት","synonyms":["type","kind","variety","sort"],"importance":8},{"pos":"Verb","root":"መሳል","word":"ከሳልክበት","synonyms":["draw","paint","sketch","depict"],"importance":6},{"pos":"Noun","root":"ማንነት","word":"ማንነት","synonyms":["identity","personality","selfhood"],"importance":9},{"pos":"Noun","root":"እህት","word":"እህቶቿንና","synonyms":["sisters"],"importance":8},{"pos":"Verb","root":"መንገር","word":"እየነገሯትና","synonyms":["tell","inform","narrate","relate"],"importance":8},{"pos":"Verb","root":"መምከር","word":"እየመከሯት","synonyms":["advise","counsel","suggest","exhort"],"importance":8},{"pos":"Noun","root":"ሐበሻ","word":"ሐበሽን","synonyms":["Abyssinian","Ethiopian"],"importance":7},{"pos":"Verb","root":"መስረቅ","word":"እንዲሰርቅ","synonyms":["steal","rob","thieve","pilfer"],"importance":7},{"pos":"Noun","root":"አልቃይዳ","word":"የዓልቃይዳ","synonyms":["Al-Qaeda"],"importance":6},{"pos":"Noun","root":"አሰለጣጠን","word":"አሰለጣጠንም","synonyms":["training method","system of training","methodology"],"importance":7}],"summary":"The batch was processed with several corrections. 'ዳጲ' and 'ጋላሀቲ' were discarded as they appeared to be either proper names without clear dictionary roots or OCR noise. 'አይየነት' was corrected to the standard 'ዓይነት' (type), and 'ማንንነት' was corrected to 'ማንነት' (identity) by removing the redundant 'ን'. Agglutinated forms containing the conjunction 'ና' (and) or the suffix 'ም' (also) were lemmatized to their core citation forms (e.g., 'እህቶቿንና' to 'እህት'). Verbs with complex prefixes like 'እንደሚሠለጥኑበት' were successfully reduced to their infinitive roots (e.g., 'መሰልጠን').","input_words":["ያጠበቀውም","እንጠየፈው","ተሰነጠቀና","እንደሚሠለጥኑበት","ያሰፈርኳት","ዳጲ","ያፅናህ","መግለጫዬን","አልነፈኩትም","የሚያሰኛቸውንና","የሚገፋፋቸውንም","መውደቂያችን","በኮርፖሬሽኑና","ያደረገዋልም","ትፈልጋችኋለች","ማመልከቻዎችና","ለማያሰናብት","ይደግፉዋቸው","የነጠቀቻት","አይየነት","ከሳልክበት","ማንንነት","እህቶቿንና","እየነገሯትና","እየመከሯት","ሐበሽን","እንዲሰርቅ","የዓልቃይዳ","ጋላሀቲ","አሰለጣጠንም"],"batch_number":null,"batch_label":null,"model_version":null},{"id":"bb4d3bcd-fafa-4f0f-aa27-3c407496ed64","created_at":"2026-02-25T20:19:46.714023+00:00","word":null,"source_file":"rare_words_18/chunk_0454.txt","batch_index":0,"words":[{"pos":"Pronoun","root":"ምን","word":"ምን","synonyms":["what","which"],"importance":9},{"pos":"Verb","root":"መቸገር","word":"ቸገረን","synonyms":["to be troubled","to be in difficulty","to be bothered"],"importance":7},{"pos":"Noun","root":"ጀልባ","word":"በጀልባቸው","synonyms":["boat","vessel","canoe"],"importance":6},{"pos":"Adjective","root":"ጉደኛ","word":"ጉደኛው","synonyms":["strange","wonderful","eccentric","extraordinary"],"importance":6},{"pos":"Verb","root":"መለመድ","word":"ይለመድሃል","synonyms":["to get used to","to become a habit","to be accustomed"],"importance":5},{"pos":"Verb","root":"ማለቅ","word":"ካለቀ","synonyms":["to finish","to end","to be depleted"],"importance":5},{"pos":"Verb","root":"መነገድ","word":"እንደሚነግዱ","synonyms":["to trade","to do business","to commerce"],"importance":7},{"pos":"Verb","root":"መብላት","word":"እየተበላችሁ","synonyms":["to be eaten","to be consumed"],"importance":6},{"pos":"Noun","root":"መሰደብ","word":"መሰደባችሁ","synonyms":["being insulted","revilement","verbal abuse"],"importance":6},{"pos":"Verb","root":"መውረድ","word":"እየወረደ","synonyms":["descending","going down","falling"],"importance":5},{"pos":"Verb","root":"መከርቸም","word":"የከረቸሙትን","synonyms":["to bolt","to lock securely","to shut tight"],"importance":7},{"pos":"Verb","root":"መክፈት","word":"ሊከፍቱ","synonyms":["to open","to unlock","to reveal"],"importance":8},{"pos":"Noun","root":"ባል","word":"ባልዋን","synonyms":["husband","spouse"],"importance":7},{"pos":"Verb","root":"መሸራረፍ","word":"የሚሸራረፈው","synonyms":["chipping away","eroding","fragmenting"],"importance":6},{"pos":"Verb","root":"ማጠናቀቅ","word":"እንድናጠናቅቃቸው","synonyms":["to complete","to finish","to finalize"],"importance":8},{"pos":"Verb","root":"መጻፍ","word":"እስከጻፍኩበት","synonyms":["to write","to record"],"importance":7},{"pos":"Verb","root":"መግባት","word":"አልገባልኝም","synonyms":["to understand","to comprehend","to enter"],"importance":9},{"pos":"Verb","root":"መፀፀት","word":"የሚፀፅተኝ","synonyms":["to regret","to feel remorse","to repent"],"importance":7},{"pos":"Noun","root":"እግር","word":"በእግሯ","synonyms":["foot","leg"],"importance":6},{"pos":"Verb","root":"ማላገጥ","word":"ስታላቁጥ","synonyms":["to mock","to sneer","to ridicule"],"importance":6},{"pos":"Noun","root":"ሕጻንነት","word":"በሕጻንነቷ","synonyms":["childhood","infancy"],"importance":7},{"pos":"Verb","root":"መንቀል","word":"መንቅዬ","synonyms":["to uproot","to pluck","to extract"],"importance":6},{"pos":"Verb","root":"መገዘት","word":"ለተገዘተ","synonyms":["to excommunicate","to curse","to swear"],"importance":5},{"pos":"Noun","root":"ዊልቸር","word":"ዊልቸር","synonyms":["wheelchair"],"importance":8},{"pos":"Verb","root":"ማጥላት","word":"አጥልቶባቸው","synonyms":["to overshadow","to cast a shadow","to darken"],"importance":6},{"pos":"Verb","root":"ማሰብ","word":"ማሰቡን","synonyms":["thinking","contemplating","considering"],"importance":8},{"pos":"Verb","root":"መፈራረቅ","word":"ይፈራረቅብኛል","synonyms":["to alternate","to take turns","to rotate"],"importance":7}],"summary":"The batch was processed by splitting merged forms like 'ምንቸገረን' into 'ምን' and 'ቸገረን'. Visual OCR errors were corrected, specifically 'ፊልቸር' to 'ዊልቸር' (wheelchair) and 'ባልድዋን' to 'ባልዋን' (her husband). Suffixes like the conjunction '-ና' and the emphasis '-ም' were stripped to isolate the core words. Non-Amharic noise such as 'ኤችቲቢ' (HTB) and unfixable fragments like 'ለአር' and 'ከባክድ' were discarded. Lemmatization was performed to provide the citation form (መነሻ ቃል) for all verbs and nouns. Redundant entries were merged.","input_words":["ምንቸገረን","በጀልባቸው","ጉደኛውና","ይለመድሃል","ካለቀም","እንደሚነግዱና","እንደሚነግዱ","እየተበላችሁ","መሰደባችሁና","እየወረደም","የከረቸሙትን","ሊከፍቱና","ባልድዋን","ለአር","ከባክድ","የሚሸራረፈው","እንድናጠናቅቃቸው","እስከጻፍኩበት","አልገባልኝም","የሚፀፅተኝና","በእግሯም","ስታላቁጥ","በሕጻንነቷ","መንቅዬ","ለተገዘተ","ኤችቲቢ","ፊልቸር","አጥልቶባቸው","ማሰቡንና","ይፈራረቅብኛል"],"batch_number":null,"batch_label":null,"model_version":null},{"id":"3654c79b-e8d2-445c-b8b7-bd855cbdedca","created_at":"2026-02-25T20:22:20.690811+00:00","word":null,"source_file":"rare_words_18/chunk_0453.txt","batch_index":0,"words":[{"pos":"Verb","root":"ማዋል","word":"የሚያውሏቸውን","synonyms":["spend","utilize","employ","use"],"importance":7},{"pos":"Verb","root":"ማቀናበር","word":"እንዲያቀናብሩ","synonyms":["coordinate","organize","arrange","edit","synthesize"],"importance":8},{"pos":"Verb","root":"መስጠት","word":"ያልሰጠኋቸውና","synonyms":["give","provide","offer"],"importance":7},{"pos":"Verb","root":"ማካፈል","word":"አካፈልኩ","synonyms":["share","divide","distribute","partition"],"importance":8},{"pos":"Verb","root":"መጋነን","word":"ተጋነነም","synonyms":["exaggerate","overstate","magnify"],"importance":6},{"pos":"Noun","root":"አገር","word":"አገር","synonyms":["country","nation","land"],"importance":9},{"pos":"Verb","root":"ማቆም","word":"ያቆመንን","synonyms":["stop","halt","establish","set up"],"importance":7},{"pos":"Verb","root":"መጨመር","word":"የማይጨመሩልን","synonyms":["add","increase","include","augment"],"importance":7},{"pos":"Adverb","root":"ዘፈቀደ","word":"በዘፈቀደ","synonyms":["randomly","arbitrarily","haphazardly"],"importance":6},{"pos":"Verb","root":"መጋራት","word":"እየተጋራው","synonyms":["share","partake","participate"],"importance":7},{"pos":"Verb","root":"መርገድ","word":"አረገደ","synonyms":["dance","sway","rhythmically move"],"importance":5},{"pos":"Noun","root":"ግዴታ","word":"ግዴታቸው","synonyms":["obligation","duty","requirement","responsibility"],"importance":8},{"pos":"Verb","root":"መመልከት","word":"ይመለከተዋልም","synonyms":["concern","regard","look","observe"],"importance":8},{"pos":"Noun","root":"ተሰጥኦ","word":"ተሰጥኦዋችን","synonyms":["talent","gift","aptitude","skill"],"importance":9},{"pos":"Noun","root":"ዳያስፖራ","word":"ዳይስፖራ","synonyms":["diaspora","expatriates"],"importance":7},{"pos":"Verb","root":"መግደል","word":"ገደለችኝ","synonyms":["kill","murder","slay"],"importance":6},{"pos":"Noun","root":"ሻምፒዮንስ","word":"ሻምፒዮንስ","synonyms":["champions","winners"],"importance":6},{"pos":"Verb","root":"መኖር","word":"አለሁ","synonyms":["exist","live","be present"],"importance":7},{"pos":"Noun","root":"ካልዛጊን","word":"ካልዛጊንን","synonyms":["Kalzagin","Proper Name"],"importance":4},{"pos":"Verb","root":"መብለጥ","word":"እንደሚበልጠውም","synonyms":["exceed","surpass","excel","be better"],"importance":8},{"pos":"Verb","root":"ማስታወስ","word":"አስታውሼያት","synonyms":["remember","recall","remind"],"importance":8},{"pos":"Verb","root":"ማቃጠል","word":"ያቃጥላቸው","synonyms":["burn","ignite","scorch"],"importance":6},{"pos":"Verb","root":"ማጥፋት","word":"ያጠፋበት","synonyms":["destroy","extinguish","erase","delete"],"importance":7},{"pos":"Verb","root":"ማጉረጥረጥ","word":"የሚያጉረጠርጥ","synonyms":["glare","stare","look fiercely"],"importance":5},{"pos":"Noun","root":"ምንትዋብ","word":"ምንትዋብም","synonyms":["Mintwab","Proper Name"],"importance":6},{"pos":"Verb","root":"ማነጽ","word":"አሳንፀዋል","synonyms":["build","construct","erect","establish"],"importance":8},{"pos":"Conjunction","root":"እንዲሁም","word":"እንዲሁም","synonyms":["also","likewise","furthermore","as well"],"importance":9},{"pos":"Verb","root":"መጻፍ","word":"ከሚጽፉላቸው","synonyms":["write","compose","author"],"importance":8},{"pos":"Verb","root":"ማስተናገድ","word":"የተስተናገደ","synonyms":["host","serve","accommodate","entertain"],"importance":8},{"pos":"Noun","root":"ሩጫ","word":"የሩጫዬን","synonyms":["race","run","sprint"],"importance":7}],"summary":"The batch was processed with high fidelity. Key actions included splitting 'እንደአገርና' into its constituent noun 'አገር' and correcting the OCR error 'ማንዲሁም' to the standard conjunction 'እንዲሁም'. Lemmatization focused on identifying the infinitive forms (መነሻ ቃል) for complex verbal structures like 'የሚያውሏቸውን' (ማዋል) and 'የተስተናገደ' (ማስተናገድ). Proper nouns like 'ምንትዋብ' and 'ካልዛጊን' were preserved. All single-character particles were filtered out per Protocol 7.","input_words":["የሚያውሏቸውን","እንዲያቀናብሩ","ያልሰጠኋቸውና","አካፈልኩ","ተጋነነም","እንደአገርና","ያቆመንን","የማይጨመሩልን","በዘፈቀድ","እየተጋራው","አረገደ","ከግዴታቸው","ይመለከተዋልም","ተሰጥኦዋችን","በዳይስፖራ","ገደለችኝ","ወደሻምፒዮንስ","እስከአለሁ","ካልዛጊንን","እንደሚበልጠውም","አስታውሼያት","ያቃጥላቸው","ወደሚያጠፋበት","የሚያጉረጠርጥ","ምንትዋብም","አሳንፀዋል","ማንዲሁም","ከሚጽፉላቸው","የተስተናገደ","የሩጫዬን"],"batch_number":null,"batch_label":null,"model_version":null},{"id":"23c32da4-0871-4e1b-b732-99c76bed9bbb","created_at":"2026-02-25T20:24:43.631392+00:00","word":null,"source_file":"rare_words_18/chunk_0448.txt","batch_index":0,"words":[{"pos":"Noun","root":"ግራ ቤት","word":"ግራቤት","synonyms":["left wing","left side","left house"],"importance":5},{"pos":"Noun","root":"ፖሊሲ","word":"በፖሊሲ","synonyms":["by policy","strategically","according to plan"],"importance":8},{"pos":"Verb","root":"ማውራት","word":"ያዋራቸውና","synonyms":["and he talked to them","conversed","discussed"],"importance":6},{"pos":"Verb","root":"ማለቅ","word":"ሲያልቅላት","synonyms":["when it ends for her","finishes","concludes"],"importance":5},{"pos":"Noun","root":"ሥዕል","word":"ሥዕሎቿ","synonyms":["her paintings","her drawings","her artwork"],"importance":7},{"pos":"Verb","root":"ማዘናጋት","word":"የሚያዘናጉትን","synonyms":["those that distract","misleading","diverting"],"importance":6},{"pos":"Verb","root":"ማራዘም","word":"በማራዘም","synonyms":["by extending","prolonging","delaying"],"importance":7},{"pos":"Noun","root":"ፍንጣሪ","word":"ፍንጣሪውን","synonyms":["the spark","the splinter","the fragment"],"importance":4},{"pos":"Verb","root":"ማጠናቀቅ","word":"በማጠናቀቅ","synonyms":["by finishing","completing","finalizing"],"importance":8},{"pos":"Verb","root":"ማውራት","word":"እንድታወራኝ","synonyms":["so she talks to me","to speak with me"],"importance":5},{"pos":"Noun","root":"ቀጠሮ","word":"ያለቀጠሮና","synonyms":["without appointment","unscheduled","unexpectedly"],"importance":6},{"pos":"Noun","root":"መፈለግ","word":"ያለአፋላጊ","synonyms":["without a seeker","unclaimed","unsearched"],"importance":5},{"pos":"Verb","root":"መጥራት","word":"ለጠራችሁት","synonyms":["for those you called","for the invited","summoned"],"importance":6},{"pos":"Verb","root":"ማቅረብ","word":"አቅርቡለት","synonyms":["present to him","offer to him","provide for him"],"importance":7},{"pos":"Verb","root":"ማለት","word":"ማለት","synonyms":["to say","meaning","signify"],"importance":9},{"pos":"Verb","root":"መድከም","word":"በሚደክሙት","synonyms":["by those who are tired","the weary","the exhausted"],"importance":5},{"pos":"Verb","root":"ማዘዋወር","word":"እናዘዋውርዎ","synonyms":["let us transfer you","move you","circulate you"],"importance":6},{"pos":"Noun","root":"ሎሚ","word":"ሎሚ","synonyms":["lemon","lime","citrus"],"importance":4},{"pos":"Verb","root":"መለጠፍ","word":"የመለጠፉ","synonyms":["of the sticking","posting","gluing"],"importance":5},{"pos":"Noun","root":"ምርመራ","word":"ምርመራ","synonyms":["investigation","examination","research"],"importance":9},{"pos":"Verb","root":"ማጨብጨብ","word":"ሲያስጨበጭብ","synonyms":["making them applaud","causing cheers","clapping"],"importance":5},{"pos":"Verb","root":"መጮህ","word":"ሲያስጮህ","synonyms":["making it sound","causing a scream","making noise"],"importance":5},{"pos":"Verb","root":"መብላት","word":"ሲያባላ","synonyms":["causing conflict","making them fight","pitting against"],"importance":6},{"pos":"Verb","root":"መደላት","word":"የሚደላቸው","synonyms":["those who are comfortable","the well-off","satisfied"],"importance":6},{"pos":"Noun","root":"ፅጌረዳ","word":"ለፅጌረዳና","synonyms":["for the rose","for the flower"],"importance":4},{"pos":"Noun","root":"አሮጌ","word":"አሮጌት","synonyms":["old woman","elderly female","hag"],"importance":5},{"pos":"Noun","root":"ድርሰት","word":"በድርሰትም","synonyms":["also in composition","in writing","in literature"],"importance":7},{"pos":"Verb","root":"ማስተዋወቅ","word":"አስተዋወቀ","synonyms":["introduced","presented","made known"],"importance":8},{"pos":"Verb","root":"መለየት","word":"ሊለያየው","synonyms":["to separate it","to distinguish it","to divide it"],"importance":6},{"pos":"Noun","root":"መፍትሄ","word":"መፍትሄዎች","synonyms":["solutions","remedies","fixes"],"importance":9},{"pos":"Noun","root":"ማህበረሰብ","word":"ማህበረሰቡን","synonyms":["the society","the community","the public"],"importance":10}],"summary":"The batch contained several OCR-induced truncations and spelling errors. 'አቅርቡለትማለት' was identified as a merged string and split into 'አቅርቡለት' and 'ማለት'. Truncated words like 'በማጠናቀ' and 'አስተዋውቀ' were restored to their full forms 'በማጠናቀቅ' and 'አስተዋወቀ'. Visual confusions such as 'በማሬዝ' (likely 'በማራዘም'), 'ምርማሮ' ('ምርመራ'), and 'መፍሄዎች' ('መፍትሄዎች') were corrected based on morphological probability. The lemmatization process successfully mapped complex verbal forms like 'ሲያባላ' and 'የሚደላቸው' to their respective citation forms 'መብላት' and 'መደላት'. All single-character noise was filtered out.","input_words":["ግራቤት","በፖለሲ","ያዋራቸውና","ሲያልቅላት","ሥዕሎቿ","የሚያዘናጉትን","በማሬዝ","ፍንጣሪውን","በማጠናቀ","እንድታወራኝ","ያለቀጠሮና","ያለአፋላጊ","ለጠራችሁት","አቅርቡለትማለት","በሚደክሙት","እናዘዋውርዎ","ሎሞን","የመለጠፉ","ምርማሮ","ሲያስጨበጭብ","ሲያስጮህ","ሲያባላ","የሚደላቸው","ለፅጌረዳና","አሮጌት","በድርሠትም","አስተዋውቀ","ሊለያየው","መፍሄዎች","ማሀበረሰቡን"],"batch_number":null,"batch_label":null,"model_version":null},{"id":"5aec7d23-e9e3-4d6c-bf2b-0f492e004504","created_at":"2026-02-25T20:25:57.58206+00:00","word":null,"source_file":"rare_words_18/chunk_0456.txt","batch_index":0,"words":[{"pos":"Verb","root":"መገላገል","word":"ገላግለውኛል","synonyms":["relieved","rescued","delivered","freed"],"importance":8},{"pos":"Noun","root":"መንበር","word":"የመንበሩም","synonyms":["throne","seat","chair","authority"],"importance":7},{"pos":"Verb","root":"ማሳዘን","word":"ቢያሳዝኑትም","synonyms":["saddened","grieved","disappointed"],"importance":6},{"pos":"Verb","root":"መውሰድ","word":"እንደወሰዷቸውና","synonyms":["took","carried","removed"],"importance":7},{"pos":"Noun","root":"ጅሎ","word":"ጅሎና","synonyms":["Jilo (Proper Name)"],"importance":4},{"pos":"Noun","root":"ሸዋየነሽ","word":"ሸዋየነሽ","synonyms":["Shewayenesh (Proper Name)"],"importance":4},{"pos":"Verb","root":"መምራት","word":"ስለሚመሯቸው","synonyms":["lead","guide","direct","manage"],"importance":8},{"pos":"Noun","root":"ሕልውና","word":"ሕልውናችን","synonyms":["existence","survival","being"],"importance":10},{"pos":"Verb","root":"ማገባደድ","word":"ሲያገባድዱ","synonyms":["concluding","finishing","wrapping up"],"importance":7},{"pos":"Noun","root":"እቅድ","word":"ለእቅዱም","synonyms":["plan","scheme","project","design"],"importance":9},{"pos":"Noun","root":"ሳልኸርስት","word":"ሳልኸርስት","synonyms":["Sunhurst (Transliterated Name)"],"importance":3},{"pos":"Noun","root":"ውለታ","word":"ውለታዎቹ","synonyms":["favors","kindness","debts of gratitude"],"importance":8},{"pos":"Noun","root":"ስፖርት","word":"ስፖርቶቿን","synonyms":["sports","athletics","games"],"importance":6},{"pos":"Verb","root":"ማክበር","word":"ካላከበርክ","synonyms":["respect","honor","celebrate"],"importance":8},{"pos":"Verb","root":"ማከናወን","word":"የሚያከናውና","synonyms":["performing","executing","accomplishing"],"importance":8},{"pos":"Verb","root":"ማቀፍ","word":"የሚያቅፉት","synonyms":["embrace","include","hug","encompass"],"importance":7},{"pos":"Verb","root":"መጎርመስ","word":"መጎርመስ","synonyms":["reaching puberty","maturing","adolescence"],"importance":6},{"pos":"Verb","root":"ማስጠጋት","word":"በማስጠጋቷ","synonyms":["sheltering","bringing close","harboring"],"importance":7},{"pos":"Noun","root":"መጽሔት","word":"መጽሔቶቻችሁን","synonyms":["magazines","journals","periodicals"],"importance":7},{"pos":"Adjective","root":"ጠራራ","word":"ከጠራራውና","synonyms":["scorching","bright","clear"],"importance":6},{"pos":"Verb","root":"መከለል","word":"እከልላቸው","synonyms":["fence","protect","shield","demarcate"],"importance":7},{"pos":"Verb","root":"ማጨለም","word":"አጨልሟል","synonyms":["darkened","obscured","dimmed"],"importance":7},{"pos":"Verb","root":"ማቀራመት","word":"ሲያቀራምት","synonyms":["devouring","consuming","eating up"],"importance":6},{"pos":"Verb","root":"መምጣት","word":"ለሚመጣና","synonyms":["coming","arriving","approaching"],"importance":8},{"pos":"Noun","root":"ኪዩባ","word":"ኪዩባ","synonyms":["Cuba"],"importance":5},{"pos":"Noun","root":"ድርደራ","word":"ድርደራቸውን","synonyms":["arrangement","stacking","alignment"],"importance":7},{"pos":"Noun","root":"አራቂ","word":"አራቂም","synonyms":["reconciler","mediator","peacemaker"],"importance":8},{"pos":"Verb","root":"መግባት","word":"ይግቡማ","synonyms":["enter","come in","join"],"importance":6},{"pos":"Verb","root":"ማስጠረግ","word":"እያስጠረገ","synonyms":["causing to sweep","clearing","cleaning"],"importance":6},{"pos":"Verb","root":"ማስፈለግ","word":"ከሚያስፈልጋችሁ","synonyms":["needed","required","necessary"],"importance":9}],"summary":"The batch was processed with high linguistic fidelity. Visual OCR errors were corrected, specifically 'ውለታበዎቹ' which was identified as 'ውለታዎቹ' based on common character confusion. Proper nouns like 'ሳልኸርስት' and 'ኪዩባ' were preserved. Morphological analysis was applied to extract citation forms (Infinitive/መነሻ ቃል) for complex verbs such as 'ገላግለውኛል' and 'ሲያቀራምት'. All entries meet the minimum character length requirement and have been assigned appropriate grammatical tags and importance scores based on semantic weight.","input_words":["ገላግለውኛል","የመንበሩም","ቢያሳዝኑትም","እንደወሰዷቸውና","ጅሎና","ሸዋየነሽ","ስለሚመሯቸው","ሕልውናችን","ሲያገባድዱ","ለእቅዱም","ሳልኸርስት","ውለታበዎቹ","ስፖርቶቿን","ካላከበርክ","የሚያከናውና","የሚያቅፉት","መጎርመስ","በማስጠጋቷ","መጽሔቶቻችሁን","ከጠራራውና","እከልላቸው","አጨልሟል","ሲያቀራምት","ለሚመጣና","ኪዩባ","ድርደራቸውን","አራቂም","ይግቡማ","እያስጠረገ","ከሚያስፈልጋቸሁ"],"batch_number":null,"batch_label":null,"model_version":null},{"id":"353ec8a2-70c3-4e96-b81f-300b1953ed02","created_at":"2026-02-25T20:30:34.771112+00:00","word":null,"source_file":"rare_words_18/chunk_0459.txt","batch_index":0,"words":[{"pos":"Adjective","root":"ኢንታንጀብል","word":"ኢንታንጀብል","synonyms":["intangible","non-physical","abstract"],"importance":6},{"pos":"Verb","root":"ማሰልጠን","word":"ማሰልጠን","synonyms":["train","coach","instruct","drill"],"importance":8},{"pos":"Noun","root":"አቪዬሽን","word":"አቪዬሽን","synonyms":["aviation","aeronautics","flight"],"importance":7},{"pos":"Verb","root":"ማሳፈር","word":"ያሳፍርሃል","synonyms":["shame","embarrass","humiliate","disgrace"],"importance":7},{"pos":"Verb","root":"ማውጣት","word":"ባወጣሽ","synonyms":["extract","remove","issue","publish"],"importance":8},{"pos":"Verb","root":"ማስመሰል","word":"እንዳታስመስሉብኝ","synonyms":["simulate","pretend","imitate","feign"],"importance":7},{"pos":"Verb","root":"ማቅመስ","word":"ላቀምሳቸው","synonyms":["taste","sample","give a taste"],"importance":6},{"pos":"Verb","root":"መጠንቀቅ","word":"መጠንቀቁ","synonyms":["caution","beware","be careful","heed"],"importance":8},{"pos":"Noun","root":"ቢስክሌት","word":"ቢስክሌት","synonyms":["bicycle","bike","cycle"],"importance":6},{"pos":"Verb","root":"መጠበቅ","word":"እንደማይጠብቀን","synonyms":["wait","expect","guard","anticipate"],"importance":9},{"pos":"Verb","root":"ማጠናቀቅ","word":"ያላጠናቀቃቸው","synonyms":["finish","complete","finalize","conclude"],"importance":8},{"pos":"Noun","root":"ፕሮዳክሽን","word":"ፕሮዳክሽኖችን","synonyms":["production","manufacturing","creation"],"importance":7},{"pos":"Noun","root":"ሲዳሞ","word":"ለሲዳሞ","synonyms":["Sidamo","Sidama"],"importance":5},{"pos":"Noun","root":"ባለቤት","word":"ለባለቤቱዋ","synonyms":["owner","spouse","proprietor","husband","wife"],"importance":8},{"pos":"Verb","root":"ማገልገል","word":"ባገለገለ","synonyms":["serve","function","assist","work"],"importance":8},{"pos":"Preposition","root":"ወደ","word":"ወደ","synonyms":["to","towards","into"],"importance":4},{"pos":"Conjunction","root":"እና","word":"እና","synonyms":["and","plus","also"],"importance":4},{"pos":"Verb","root":"መሸሽ","word":"እሸሽ","synonyms":["flee","escape","run away","avoid"],"importance":7},{"pos":"Verb","root":"መውደድ","word":"የምትወዱት","synonyms":["love","like","adore","appreciate"],"importance":9},{"pos":"Noun","root":"አዶርመንት","word":"አዶርመንት","synonyms":["adornment","decoration","ornament"],"importance":5},{"pos":"Verb","root":"መቅለል","word":"መቅለል","synonyms":["be light","be easy","be simple"],"importance":7},{"pos":"Noun","root":"አውስትሪያ","word":"አውስትሪያ","synonyms":["Austria"],"importance":5},{"pos":"Noun","root":"ጥምቀት","word":"የጥምቀቱን","synonyms":["baptism","epiphany","christening"],"importance":7},{"pos":"Verb","root":"ማውራት","word":"አወራንበት","synonyms":["talk","speak","converse","chat"],"importance":8},{"pos":"Verb","root":"ማድረስ","word":"አደረሷቸው","synonyms":["deliver","reach","convey","transport"],"importance":8},{"pos":"Verb","root":"መሻል","word":"የተሻላቸው","synonyms":["be better","improve","surpass"],"importance":8},{"pos":"Verb","root":"መምረጥ","word":"እንዳትመርጡት","synonyms":["choose","select","elect","pick"],"importance":8},{"pos":"Verb","root":"መንጋደድ","word":"መንጋደዱ","synonyms":["tilt","lean","slant","tip"],"importance":6},{"pos":"Verb","root":"መስጠት","word":"የምትሰጠውስ","synonyms":["give","provide","offer","grant"],"importance":9},{"pos":"Noun","root":"እኩሌታ","word":"እኩሌቶቹን","synonyms":["half","portion","part","moiety"],"importance":6}],"summary":"The batch was processed by splitting conjunctions (e.g., 'ና') and prepositions (e.g., 'በ') from their host words. OCR errors were corrected in 'ማስልጠን' (to ማሰልጠን) and 'መንጠንቀቁ' (to መጠንቀቁ). The word 'ሲማውል' was discarded as it appeared to be a non-standard or corrupted form that could not be reliably lemmatized. Single-character particles resulting from splits were filtered out per Protocol 7. Loanwords like 'ኢንታንጀብል' (Intangible) and 'አዶርመንት' (Adornment) were identified and lemmatized to their base forms.","input_words":["በኢንታንጀብሉም","ማስልጠን","አቪዬሽኑና","ያሳፍርሃል","ባወጣሽ","እንዳታስመስሉብኝ","ላቀምሳቸው","መንጠንቀቁ","ቢስክሌትና","እንደማይጠብቀን","ያላጠናቀቃቸው","ፕሮዳክሽኖችንም","ለሲዳሞ","ለባለቤቱዋ","ባገለገለና","ወደእና","እሸሽ","የምትወዱትና","አዶርመንት","መቅለልና","ወደአውስትሪያ","የጥምቀቱን","አወራንበትና","ሲማውል","አደረሷቸውና","የተሻላቸው","እንዳትመርጡት","መንጋደዱ","የምትሰጠውስ","እኩሌቶቹን"],"batch_number":null,"batch_label":null,"model_version":null},{"id":"508878d2-b6c6-4fcb-b93e-e174e2d93868","created_at":"2026-02-25T20:33:29.880982+00:00","word":null,"source_file":"rare_words_18/chunk_0458.txt","batch_index":0,"words":[{"pos":"Verb","root":"ማዋሰን","word":"እያዋሰነ","synonyms":["bordering","delimiting","demarcating"],"importance":6},{"pos":"Noun","root":"ኡጋንዳዊ","word":"ከኡጋንዳዊያን","synonyms":["Ugandans"],"importance":5},{"pos":"Noun","root":"ቢላ","word":"በቢላ","synonyms":["knife","blade"],"importance":4},{"pos":"Conjunction","root":"እና","word":"እና","synonyms":["and"],"importance":3},{"pos":"Noun","root":"ውርንጭላ","word":"ውርንጭላው","synonyms":["foal","young donkey","colt"],"importance":5},{"pos":"Noun","root":"በሽታ","word":"በሽታ","synonyms":["disease","illness","sickness"],"importance":8},{"pos":"Verb","root":"መቁጠር","word":"የሚቆጠር","synonyms":["counted","considered","accounted"],"importance":7},{"pos":"Noun","root":"ሮይ","word":"ከሮይ","synonyms":["Roy"],"importance":3},{"pos":"Noun","root":"እቴጌ","word":"የእቴጌንም","synonyms":["Empress","Queen Consort"],"importance":7},{"pos":"Noun","root":"ዓጽም","word":"ዓጽም","synonyms":["remains","skeleton","bone"],"importance":8},{"pos":"Verb","root":"መግዛት","word":"ቢገዟችሁ","synonyms":["if they buy you","purchase"],"importance":6},{"pos":"Noun","root":"ስዊድናዊ","word":"ስዊድናዊውን","synonyms":["Swedish","Swede"],"importance":5},{"pos":"Preposition","root":"ስለ","word":"ስለ","synonyms":["about","concerning","because of"],"importance":4},{"pos":"Noun","root":"አበበ","word":"አበበ","synonyms":["Abebe","bloomed"],"importance":4},{"pos":"Noun","root":"ኤምሲኦል","word":"ኤምሲኦል","synonyms":["MCOIL"],"importance":2},{"pos":"Verb","root":"መኩራት","word":"ኮርቼባቸዋለሁ","synonyms":["I am proud of them"],"importance":6},{"pos":"Verb","root":"ማራገብ","word":"የማራገብ","synonyms":["fanning","winnowing","ventilating"],"importance":5},{"pos":"Verb","root":"መጣጣር","word":"በተጣጣሩ","synonyms":["strove","struggled","made effort"],"importance":7},{"pos":"Noun","root":"አስቀማጭ","word":"ለአስቀማጮችም","synonyms":["depositors","investors"],"importance":6},{"pos":"Verb","root":"መበላሸት","word":"መበላሸቱንም","synonyms":["spoilage","deterioration","corruption"],"importance":7},{"pos":"Noun","root":"ሀገር","word":"ወደሀገራቸው","synonyms":["country","land","nation"],"importance":6},{"pos":"Noun","root":"ቱናይን","word":"ቱናይን","synonyms":["Tunine"],"importance":2},{"pos":"Noun","root":"ኮምዎረር","word":"ኮምዎረርን","synonyms":["Composer","Comorer"],"importance":3},{"pos":"Verb","root":"ማዳበር","word":"እንዳዳበረ","synonyms":["developed","enriched","cultivated"],"importance":7},{"pos":"Verb","root":"መሞት","word":"ስለሞትኩኝ","synonyms":["because I died"],"importance":5},{"pos":"Verb","root":"ማቆም","word":"አቆሙኝ","synonyms":["they stopped me","they made me stand"],"importance":6},{"pos":"Verb","root":"መሸጥ","word":"መሸጥክን","synonyms":["your selling","your sale"],"importance":6},{"pos":"Verb","root":"መግዛት","word":"መግዛትህን","synonyms":["your buying","your purchase"],"importance":6},{"pos":"Verb","root":"መተው","word":"የማትተው","synonyms":["that you don't leave","that you don't abandon"],"importance":7},{"pos":"Verb","root":"ማስወሰን","word":"ቢያስወስኑም","synonyms":["even if they make a decision","cause to decide"],"importance":6},{"pos":"Noun","root":"አሳዳጊ","word":"ከአሳዳጊያቸው","synonyms":["guardian","parent","nurturer"],"importance":7},{"pos":"Noun","root":"ሠንሻይን","word":"ሠንሻይን","synonyms":["Sunshine"],"importance":4},{"pos":"Verb","root":"መጠቆም","word":"እጠቆማለሁ","synonyms":["I indicate","I point out","I suggest"],"importance":6}],"summary":"The batch was processed by identifying and splitting several merged strings where the conjunction suffix '-na' was fused with nouns or verbs (e.g., 'በቢላና', 'የማራገብና'). A significant OCR error 'በሽታየሚቆጠር' was successfully split into two distinct semantic units. Lemmatization was performed globally, mapping complex conjugated verbs like 'ኮርቼባቸዋለሁ' to their infinitive roots like 'መኩራት'. Proper nouns and transliterations such as 'ኤምሲኦል' and 'ሠንሻይን' were identified and preserved. All resulting words met the minimum 2-character length requirement.","input_words":["እያዋሰነ","ከኡጋንዳዊያን","በቢላና","ውርንጭላው","በሽታየሚቆጠር","ከሮይ","የእቴጌንም","ዓጽም","ቢገዟችሁ","ስዊድናዊውን","ስለአበበ","ኤምሲኦል","ኮርቼባቸዋለሁ","የማራገብና","በተጣጣሩ","ለአስቀማጮችም","መበላሸቱንም","ወደሀገራቸውና","ቱናይንና","ኮምዎረርን","እንዳዳበረና","ስለሞትኩኝ","አቆሙኝ","መሸጥክን","መግዛትህን","የማትተው","ቢያስወስኑም","ከአሳዳጊያቸው","ሠንሻይን","እጠቆማለሁ"],"batch_number":null,"batch_label":null,"model_version":null},{"id":"c82e1784-3399-4490-a5b0-e5906639e516","created_at":"2026-02-25T20:34:04.626275+00:00","word":null,"source_file":"rare_words_18/chunk_0462.txt","batch_index":0,"words":[{"pos":"Verb","root":"መጸየፍ","word":"ተጸየፈቻት","synonyms":["to loathe","to abhor","to detest","to feel disgusted"],"importance":7},{"pos":"Noun","root":"እውነት","word":"እውነትነቱንም","synonyms":["truthfulness","authenticity","reality","veracity"],"importance":8},{"pos":"Verb","root":"መላመድ","word":"እስኪላመዱ","synonyms":["to get used to","to adapt","to familiarize","to acclimate"],"importance":6},{"pos":"Adjective","root":"ዘይቤ","word":"ከዘይቤያዊ","synonyms":["stylistic","figurative","idiomatic","metaphorical"],"importance":7},{"pos":"Noun","root":"ዲሞክራታይዜሽን","word":"የዲሞክራታይዜሽኑ","synonyms":["democratization","democratic process"],"importance":9},{"pos":"Noun","root":"ዲሞክራሲ","word":"ዲሞክራሲው","synonyms":["democracy","democratic system"],"importance":10},{"pos":"Adjective","root":"ኢትዮጵያዊ","word":"ኢትዮጵያዊ","synonyms":["Ethiopian","native of Ethiopia"],"importance":9},{"pos":"Verb","root":"መንከባከብ","word":"የሚንከባከብትን","synonyms":["to care for","to nurture","to look after","to maintain"],"importance":8},{"pos":"Verb","root":"ማስተላለፍ","word":"ሊያስተላልፉብህ","synonyms":["to transmit","to pass on","to transfer","to broadcast"],"importance":7},{"pos":"Adjective","root":"ከባድ","word":"እስከከባድ","synonyms":["heavy","serious","difficult","severe"],"importance":6},{"pos":"Verb","root":"ማወላወል","word":"ሲያወላውሉና","synonyms":["to hesitate","to waver","to vacillate","to be indecisive"],"importance":7},{"pos":"Adverb","root":"ነገ በስቲያ","word":"ከነገበስቲያ","synonyms":["day after tomorrow"],"importance":5},{"pos":"Noun","root":"ኢጣልያ","word":"ኢጣልያና","synonyms":["Italy"],"importance":6},{"pos":"Verb","root":"ማስከፈል","word":"ሚያስከፍል","synonyms":["to charge","to make pay","to exact"],"importance":7},{"pos":"Verb","root":"መንጻት","word":"መንጻትህን","synonyms":["to be purified","to be cleansed","to be sanctified"],"importance":8},{"pos":"Noun","root":"ጎጆ","word":"የየጎጆውን","synonyms":["hut","cottage","nest","small dwelling"],"importance":6},{"pos":"Noun","root":"ጠጋኝ","word":"ለጠጋኝ","synonyms":["repairer","mender","fixer","restorer"],"importance":6},{"pos":"Verb","root":"ማስመርመር","word":"ማስመርመሩ","synonyms":["to have examined","to cause to investigate","to audit"],"importance":7},{"pos":"Verb","root":"መሰናበት","word":"የተሰናበትኳቸው","synonyms":["to bid farewell","to dismiss","to say goodbye","to resign"],"importance":7},{"pos":"Verb","root":"ማገልገል","word":"የምታገለግልን","synonyms":["to serve","to minister","to work for","to function"],"importance":8},{"pos":"Verb","root":"ማምጣት","word":"ስታመጣም","synonyms":["to bring","to fetch","to produce","to cause"],"importance":8},{"pos":"Noun","root":"ፍልቃቂ","word":"ፍልቃቂዎች","synonyms":["fragment","chip","splinter","shred"],"importance":5},{"pos":"Verb","root":"ማስቆጠር","word":"ያላስቆጠሩ","synonyms":["to cause to count","to register","to score"],"importance":6},{"pos":"Verb","root":"መፈጸም","word":"የፈጸመችብንን","synonyms":["to commit","to perform","to execute","to fulfill"],"importance":8},{"pos":"Verb","root":"መድመቅ","word":"በደመቀችባቸው","synonyms":["to shine","to be bright","to be vivid","to be colorful"],"importance":7},{"pos":"Verb","root":"መዝለል","word":"አለመዝለሉንም","synonyms":["to jump","to skip","to leap","to omit"],"importance":6},{"pos":"Verb","root":"መዘግየት","word":"በመዘግየትዋ","synonyms":["to be delayed","to be late","to lag"],"importance":7},{"pos":"Noun","root":"ቺምፓንዚ","word":"በቺምፓንዚ","synonyms":["chimpanzee","ape"],"importance":5},{"pos":"Noun","root":"ጎሪላ","word":"በጎሪላ","synonyms":["gorilla","great ape"],"importance":5},{"pos":"Verb","root":"መታደስ","word":"እንዳልታደሱ","synonyms":["to be renewed","to be renovated","to be restored"],"importance":7}],"summary":"The batch was processed with a focus on morphological restoration and OCR noise reduction. Notable corrections include the removal of trailing Latin characters in 'ዲሞክራሲውN' and the phonetic correction of loanwords 'ቺፓንዚ' to 'ቺምፓንዚ' and 'ጉሬላ' to 'ጎሪላ'. Complex verbal forms like 'የተሰናበትኳቸው' and 'ሊያስተላልፉብህ' were successfully lemmatized to their infinitive citation forms. Single-character particles like 'ኮ' and 'ና' were stripped during the cleaning process to isolate the semantic core. All entries meet the minimum character length requirement.","input_words":["ተጸየፈቻት","እውነትነቱንም","እስኪላመዱ","ከዘይቤያዊ","የዲሞክራታይዜሽኑ","ዲሞክራሲውN","ኢትዮጵያዊኮ","የሚንከባከብትን","ሊያስተላልፉብህ","እስከከባድ","ሲያወላውሉና","ከነገበስቲያ","ኢጣልያና","ሚያስከፍል","መንጻትህን","የየጎጆውን","ለጠጋኝ","ማስመርመሩ","የተሰናበትኳቸው","የምታገለግልን","ስታመጣም","ፍልቃቂዎች","ያላስቆጠሩ","የፈጸመችብንን","በደመቀችባቸው","አለመዝለሉንም","በመዘግየትዋ","በቺፓንዚ","በጉሬላ","እንዳልታደሱ"],"batch_number":null,"batch_label":null,"model_version":null}]