[{"word":"ለመተኛነት","root_name":"መተኛት","pos":"Noun","synonyms":["for being a sleeper","for laziness","dormancy"]},{"word":"ለመተካት","root_name":"መተካት","pos":"Verb","synonyms":["To replace","to substitute","to succeed"]},{"word":"ለመተካትንም","root_name":"መተካት","pos":"Verb","synonyms":["replacing","substituting","succeeding"]},{"word":"ለመተኮስም","root_name":"መተኮስ","pos":"Verb","synonyms":["also to shoot","also to fire"]},{"word":"ለመተኮስና","root_name":"መተኮስ","pos":"Verb","synonyms":["shoot","fire","blast","discharge"]},{"word":"ለመተዋችን","root_name":"መተው","pos":"Verb","synonyms":["to leave","to abandon","to quit","to forsake"]},{"word":"ለመተዋወቁ","root_name":"መተዋወቅ","pos":"Verb","synonyms":["acquaintance","introduction"]},{"word":"ለመተዋወቂያ","root_name":"መተዋወቅ","pos":"Noun","synonyms":["introduction","acquaintance","getting to know"]},{"word":"ለመተዛዘል","root_name":"መተዛዘል","pos":"Verb","synonyms":["to carry each other","mutual support"]},{"word":"ለመተዛዘብ","root_name":"መተዛዘብ","pos":"Verb","synonyms":["to observe critically","to judge each other","to lose mutual respect"]}]